advanced_rpn_calculator/__init__.py
advanced_rpn_calculator/calculator.py
advanced_rpn_calculator/main.py
advanced_rpn_calculator/rpn.py
advanced_rpn_calculator-0.1.dist-info/LICENSE
advanced_rpn_calculator-0.1.dist-info/METADATA
advanced_rpn_calculator-0.1.dist-info/WHEEL
advanced_rpn_calculator-0.1.dist-info/entry_points.txt
advanced_rpn_calculator-0.1.dist-info/top_level.txt
advanced_rpn_calculator-0.1.dist-info/RECORD
