Metadata-Version: 2.1
Name: advanced-rpn-calculator
Version: 0.1
Summary: A full featured rpn calculator
Home-page: https://github.com/AkbarBadShah/advanced_rpn_calculator.git
Author: Akbar Badshah
Author-email: akbarahmadshah1@gmail.com
License: MIT
Download-URL: https://github.com/AkbarBadShah/advanced_rpn_calculator/archive/1.0.tar.gz
Keywords: rpn,practice,Polish,calculator
Platform: UNKNOWN
Classifier: Topic :: Software Development :: Build Tools
Classifier: License :: OSI Approved :: MIT License
Classifier: Programming Language :: Python :: 3
Classifier: Operating System :: OS Independent
Requires-Python: >=3.6
